{"status":"done","publicPath":"http://localhost:8080/","chunks":{"app":[{"name":"app.js","publicPath":"http://localhost:8080/app.js","path":"/Users/admin/Development/python/django_autograder/grader/grader_client/dist/app.js"},{"name":"0.607f4c289db422d4b737.hot-update.js","publicPath":"http://localhost:8080/0.607f4c289db422d4b737.hot-update.js","path":"/Users/admin/Development/python/django_autograder/grader/grader_client/dist/0.607f4c289db422d4b737.hot-update.js"}]},"error":"ModuleError","message":"(Emitted value instead of an instance of Error) \n  Error compiling template:\n  \n  <div>\n    <p>{{report}}</p>\n  \n    <div v-if=\"formattedReport.error\">\n      <P>Error running grader</p>\n        <p>{{formattedReport.message}}</p>\n    </div>\n    <div v-else>\n      <P>Messages</p>\n      <p v-for=\"msg in formattedReport\">{{msg}}</p>\n  \n      <table>\n        <th><td>Question</td><td>Test Files</td><td>Messages</td><td>Points</td><td>Adjusted Points</td><td>Comments</td></tr>\n        <tr v-for:\"question in reports\">\n          <td>{{question.number}}</td>\n          <td>{{question.testfiles}}</td>\n          <td>{{question.messages}}</td>\n          <td>{{question.points}}</td>\n          <td><input v-model:\"question.adjustedPoints\" v-on:\"adjustPoints(question.id)\"></td>\n          <td><input v-model:\"question.comments\" v-on:\"editComments(question.id)\"</td>\n          \n        </tr>\n      </table>\n  \n    </div>\n  </div>\n  \n  \n  - tag <th> has no matching end tag.\n"}